{
  "project_info": {
    "project_number": "359397830894",
    "firebase_url": "https://push-notification-66680.firebaseio.com",
    "project_id": "push-notification-66680",
    "storage_bucket": "push-notification-66680.appspot.com"
  },
  "client": [
    {
      "client_info": {
        "mobilesdk_app_id": "1:359397830894:android:56dbad85a136b1502643ff",
        "android_client_info": {
          "package_name": "com.example.pushnotif"
        }
      },
      "oauth_client": [
        {
          "client_id": "359397830894-h92bs0j30lgkifrh9dp02knbci1a52kq.apps.googleusercontent.com",
          "client_type": 3
        }
      ],
      "api_key": [
        {
          "current_key": "AIzaSyC7vKjJi951JEdtHiZP_zDfQMVbWVMrfvk"
        }
      ],
      "services": {
        "appinvite_service": {
          "other_platform_oauth_client": [
            {
              "client_id": "359397830894-h92bs0j30lgkifrh9dp02knbci1a52kq.apps.googleusercontent.com",
              "client_type": 3
            }
          ]
        }
      }
    }
  ],
  "configuration_version": "1"
}